scrapebiblio/__init__.py
scrapebiblio/convert_to_md.py
scrapebiblio/find_reference.py
scrapebiblio/utils/__init__.py
scrapebiblio/utils/convert_from_pdf_image_format.py
scrapebiblio/utils/openai_utils.py
scrapebiblio/utils/pdf_utils.py
scrapebiblio/utils/read.py
scrapebiblio/utils/reference_utils.py
scrapebiblio/utils/text_utils.py
scrapebiblio-1.2.0.dist-info/METADATA
scrapebiblio-1.2.0.dist-info/WHEEL
scrapebiblio-1.2.0.dist-info/licenses/LICENSE
scrapebiblio-1.2.0.dist-info/RECORD
