Metadata-Version: 2.3
Name: scrapebiblio
Version: 1.2.0
Summary: library for extracting reference from documents
Author-email: Marco Vinciguerra <mvincig11@gmail.com>, Marco Perini <perinim.98@gmail.com>, Lorenzo Padoan <lorenzo.padoan977@gmail.com>
License-Expression: MIT
License-File: LICENSE
Keywords: ai,artificial intelligence,gpt,graph,machine learning,natural language processing,nlp,openai,scraping,web scraping tool,webscraping
Classifier: Intended Audience :: Developers
Classifier: Operating System :: OS Independent
Classifier: Programming Language :: Python :: 3
Classifier: Topic :: Software Development :: Libraries :: Python Modules
Requires-Python: <4.0,>=3.9
Requires-Dist: browserbase>=0.1.0
Requires-Dist: gtts>=2.5.3
Requires-Dist: openai>=1.45.0
Requires-Dist: pymupdf>=1.24.10
Requires-Dist: pypdf2>=3.0.1
Requires-Dist: python-dotenv==1.0.1
Requires-Dist: requests>=2.32.3
Requires-Dist: scrapegraphai>=1.18.1
Provides-Extra: docs
Requires-Dist: furo==2024.5.6; extra == 'docs'
Requires-Dist: sphinx==6.0; extra == 'docs'
